{
  "last_updated": "2026-05-12T13:01:19.782931+00:00",
  "job_count": 1,
  "jobs": [
    {
      "id": "ctT6caRvpwUkt9RpAAAAAA==",
      "title": "Womens Health Nurse Practictioner",
      "company": "True Health NY",
      "location": "New York, New York",
      "is_remote": false,
      "date_posted": "2026-05-12T00:00:00.000Z",
      "salary": "",
      "apply_link": "https://bebee.com/us/jobs/womens-health-nurse-practictioner-true-health-ny-fresh-meadows-ny-united-states--resume-25343_3662348572",
      "description_snippet": "Job DescriptionJob DescriptionWOMENS HEALTH NURSE PRACTITIONER\n\nFull Time\n\nNew York, NY The \u201cTRUE HEALTH\u201d is a for-profit healthcare organization with 7 health centers, providing primary care and prev",
      "employer_logo": "https://encrypted-tbn0.gstatic.com/images?q=tbn:ANd9GcSbXwcWu6ewc0C2IjTADsrEQBqGBF7zaz_FGlc_&s=0"
    }
  ]
}